usdm4/__info__.py
usdm4/__init__.py
usdm4/api/__init__.py
usdm4/api/abbreviation.py
usdm4/api/activity.py
usdm4/api/address.py
usdm4/api/administrable_product.py
usdm4/api/administrable_product_property.py
usdm4/api/administration.py
usdm4/api/alias_code.py
usdm4/api/analysis_population.py
usdm4/api/api_base_model.py
usdm4/api/assigned_person.py
usdm4/api/biomedical_concept.py
usdm4/api/biomedical_concept_category.py
usdm4/api/biomedical_concept_property.py
usdm4/api/biomedical_concept_surrogate.py
usdm4/api/biospecimen_retention.py
usdm4/api/characteristic.py
usdm4/api/code.py
usdm4/api/comment_annotation.py
usdm4/api/condition.py
usdm4/api/document_content_reference.py
usdm4/api/duration.py
usdm4/api/eligibility_criterion.py
usdm4/api/encounter.py
usdm4/api/endpoint.py
usdm4/api/estimand.py
usdm4/api/extension.py
usdm4/api/geographic_scope.py
usdm4/api/governance_date.py
usdm4/api/identifier.py
usdm4/api/indication.py
usdm4/api/ingredient.py
usdm4/api/intercurrent_event.py
usdm4/api/masking.py
usdm4/api/medical_device.py
usdm4/api/narrative_content.py
usdm4/api/objective.py
usdm4/api/organization.py
usdm4/api/person_name.py
usdm4/api/population_definition.py
usdm4/api/procedure.py
usdm4/api/product_organization_role.py
usdm4/api/quantity_range.py
usdm4/api/response_code.py
usdm4/api/schedule_timeline.py
usdm4/api/schedule_timeline_exit.py
usdm4/api/scheduled_instance.py
usdm4/api/serialize.py
usdm4/api/strength.py
usdm4/api/study.py
usdm4/api/study_amendment.py
usdm4/api/study_amendment_impact.py
usdm4/api/study_amendment_reason.py
usdm4/api/study_arm.py
usdm4/api/study_cell.py
usdm4/api/study_change.py
usdm4/api/study_definition_document.py
usdm4/api/study_definition_document_version.py
usdm4/api/study_design.py
usdm4/api/study_element.py
usdm4/api/study_epoch.py
usdm4/api/study_intervention.py
usdm4/api/study_role.py
usdm4/api/study_site.py
usdm4/api/study_title.py
usdm4/api/study_version.py
usdm4/api/subject_enrollment.py
usdm4/api/substance.py
usdm4-0.14.0.dist-info/licenses/LICENSE
usdm4-0.14.0.dist-info/METADATA
usdm4-0.14.0.dist-info/WHEEL
usdm4-0.14.0.dist-info/top_level.txt
usdm4-0.14.0.dist-info/RECORD
