Metadata-Version: 2.4
Name: usdm4
Version: 0.14.0
Summary: A python package for using the CDISC TransCelerate USDM, version 4
Author: D Iberson-Hurst
Author-email: 
Classifier: Intended Audience :: Developers
Classifier: Programming Language :: Python
Classifier: Programming Language :: Python :: 3
Classifier: Programming Language :: Python :: 3.10
Classifier: Operating System :: OS Independent
License-File: LICENSE
Requires-Dist: usdm3==0.12.1
Requires-Dist: simple_error_log>=0.6.0
Requires-Dist: python-dateutil==2.9.0.post0
Dynamic: author
Dynamic: classifier
Dynamic: description
Dynamic: description-content-type
Dynamic: license-file
Dynamic: requires-dist
Dynamic: summary
